AUTHORS.rst
CONTRIBUTING.rst
HISTORY.rst
LICENSE
MANIFEST.in
README.rst
setup.cfg
setup.py
docs/Makefile
docs/authors.rst
docs/conf.py
docs/contributing.rst
docs/history.rst
docs/index.rst
docs/installation.rst
docs/make.bat
docs/readme.rst
docs/usage.rst
mountain/__init__.py
mountain/mountain.py
mountain.egg-info/PKG-INFO
mountain.egg-info/SOURCES.txt
mountain.egg-info/dependency_links.txt
mountain.egg-info/not-zip-safe
mountain.egg-info/top_level.txt
tests/test_mountain.py