Metadata-Version: 1.1
Name: mountain
Version: 0.1.0
Summary: A Flask-powered Zappa-deployed project for hosting content written in Markdown.
Home-page: https://github.com/pydanny/mountain
Author: Daniel Roy Greenfeld
Author-email: pydanny@gmail.com
License: MIT license
Keywords: mountain
Platform: UNKNOWN
Classifier: Development Status :: 2 - Pre-Alpha
Classifier: Intended Audience :: Developers
Classifier: License :: OSI Approved :: MIT License
Classifier: Natural Language :: English
Classifier: Programming Language :: Python :: 2
Classifier: Programming Language :: Python :: 2.7
Classifier: Programming Language :: Python :: 3
Classifier: Programming Language :: Python :: 3.4
Classifier: Programming Language :: Python :: 3.5
Classifier: Programming Language :: Python :: 3.6
